odoo/addons/community_maps/__init__.py
odoo/addons/community_maps/__manifest__.py
odoo/addons/community_maps/controllers/__init__.py
odoo/addons/community_maps/controllers/cm_map_controller.py
odoo/addons/community_maps/controllers/cm_submission_transfer_controller.py
odoo/addons/community_maps/data/collect_place_submission_email_template.xml
odoo/addons/community_maps/models/__init__.py
odoo/addons/community_maps/models/cm_button_color_config.py
odoo/addons/community_maps/models/cm_crowdfunding_notification.py
odoo/addons/community_maps/models/cm_crowdfunding_notification_request.py
odoo/addons/community_maps/models/cm_external_id_mixin.py
odoo/addons/community_maps/models/cm_filter.py
odoo/addons/community_maps/models/cm_filter_group.py
odoo/addons/community_maps/models/cm_form_model.py
odoo/addons/community_maps/models/cm_form_submission.py
odoo/addons/community_maps/models/cm_form_submission_metadata.py
odoo/addons/community_maps/models/cm_form_submission_transfer_request.py
odoo/addons/community_maps/models/cm_map.py
odoo/addons/community_maps/models/cm_map_colorschema.py
odoo/addons/community_maps/models/cm_map_social_item.py
odoo/addons/community_maps/models/cm_partner.py
odoo/addons/community_maps/models/cm_place.py
odoo/addons/community_maps/models/cm_place_category.py
odoo/addons/community_maps/models/cm_place_child.py
odoo/addons/community_maps/models/cm_place_external_link.py
odoo/addons/community_maps/models/cm_place_presenter_metadata.py
odoo/addons/community_maps/models/cm_presenter_model.py
odoo/addons/community_maps/models/cm_slug_id_mixin.py
odoo/addons/community_maps/models/cm_utils.py
odoo/addons/community_maps/security/ir.model.access.csv
odoo/addons/community_maps/security/rules.xml
odoo/addons/community_maps/services/__init__.py
odoo/addons/community_maps/services/cm_map_forms_service.py
odoo/addons/community_maps/services/cm_map_service.py
odoo/addons/community_maps/static/src/img/community_maps_odoo_icon.png
odoo14_addon_community_maps-14.0.0.2.8.dist-info/METADATA
odoo14_addon_community_maps-14.0.0.2.8.dist-info/WHEEL
odoo14_addon_community_maps-14.0.0.2.8.dist-info/top_level.txt
odoo14_addon_community_maps-14.0.0.2.8.dist-info/RECORD
