Metadata-Version: 2.1
Name: odoo14-addon-community-maps
Version: 14.0.0.2.8
Summary: Module to create and manage your map visualizations into a website
Home-page: https://gitlab.com/coopdevs/community-maps-builder-backend
Author: Coopdevs Treball SCCL
Classifier: Programming Language :: Python
Classifier: Framework :: Odoo
Classifier: Framework :: Odoo :: 14.0
Requires-Python: >=3.6
Requires-Dist: odoo14-addon-base-rest
Requires-Dist: odoo14-addon-base-rest-base-structure
Requires-Dist: odoo14-addon-metadata
Requires-Dist: odoo14-addon-queue-job
Requires-Dist: odoo <14.1dev,>=14.0a
